[
    {
        "verse": "1",
        "devanagari": "मैत्रेय उवाच । एवं निशम्य कपिलस्य वचो जनित्री । सा कर्दमस्य दयिता किल देवहूतिः । विस्रस्तमोहपटला तमभिप्रणम्य । तुष्टाव तत्त्वविषयाङ्कित ...",
        "english_devnagari": "maitreya uvācaevaṃ niśamya kapilasya vaco janitrīsā kardamasya dayitā kila devahūtiḥvisrastamohapaṭalā tamabhipraṇamyatuṣṭāva tattvaviṣayāṅkita siddhibhūmim",
        "verse_Syn": [
            "maitreya",
            "uvāca",
            "evam",
            "niśam",
            "ya",
            "kapilasya",
            "vaco",
            "janitrī",
            "sā",
            "kardamasya",
            "dayitā",
            "kila",
            "devahūtiḥ",
            "visrastam",
            "oha",
            "paṭalā",
            "tamabhipraṇamya",
            "tuṣṭāva",
            "tattva",
            "viṣayā",
            "aṅkita",
            "siddhibhūmim"
        ],
        "translation": "Maitreya said:\nHaving heard the discourse of Kapila, his mother Devahūti, the (beloved) wife of Kardama, got her veil of delusion torn open. She bowed to him and praised him who was the founder (lit. land) of the Sāṃkhya (system of philosophy) which is mainly characterised by the topic—treatment of Tattvas (principles).[1]",
        "purport": "Footnote [1]:\ntattva-viṣayāṅkita-siddha-bhūmim.\n(i) Kapila was the patron of Yogins who are famous for their knowledge of the Tattvas viz. Prakṛti, Puruṣa and others—VṚ.\n(ii) Kapila was the supporter of Brahmā and other numerous Śiddhas who are devoted to the Tattva, viz., Viṣṇu.—Padaratnāvalī\n(iii) Kapila is so called because he was the past master in the Bhakti- tattva, Sāṃkhya-System, Yoga-tattva etc.—VC.\n(iv) Kapila was the asylum of Siḍḍhis which are characterised by Vaiṣṇava-Sāṃkhya the main subject of which are the Tattvas, viz., cit. acit Brahman.—Siddhāntapradīpa\n(v) Kapila was the preceptor of Siddhas who are characterised by the knowledge of Tattvas, viz., Prakṛti, Puruṣa, Īśvara etc.—Bālaprabodhini"
    },
    {
        "verse": "2",
        "devanagari": "देवहूतिरुवाच । अथाप्यजोऽन्तःसलिले शयानं । भूतेन्द्रियार्थात्ममयं वपुस्ते । गुणप्रवाहं सदशेषबीजं । दध्यौ स्वयं यत् जठराब्जजातः ॥ २ ॥",
        "english_devnagari": "devahūtiruvācaathāpyajo'ntaḥsalile śayānaṃbhūtendriyārthātmamayaṃ vapusteguṇapravāhaṃ sadaśeṣabījaṃdadhyau svayaṃ yat jaṭharābjajātaḥ",
        "verse_Syn": [
            "devahūtir",
            "uvāca",
            "athāpya",
            "ajo'",
            "antaḥsalile",
            "śayānam",
            "bhūte",
            "indriyārthāt",
            "mama",
            "yam",
            "vapus",
            "te",
            "guṇa",
            "pravāham",
            "sadaśe",
            "iṣa",
            "bījam",
            "dadhyau",
            "svayam",
            "yat",
            "jaṭharā",
            "abjajāt",
            "aḥ"
        ],
        "translation": "Devahūti said:\nEven god Brahmā himself who was born of the lotus in your stomach (could not see your body but mentally) meditated upon your person which was lying manifest in the cosmic waters; which was the cause of the entire universe; which consisted of bhūtas (elements), sense-organs and their objects (e.g. fragrance, taste etc.), and the mind, and which has the flow (Sattva, Rajas, Tamas) in it.",
        "purport": ""
    },
    {
        "verse": "3",
        "devanagari": "स एव विश्वस्य भवान् विधत्ते । गुणप्रवाहेण विभक्तवीर्यः । सर्गाद्यनीहोऽवितथाभिसन्धिः । आत्मेश्वरोऽतर्क्य सहस्रशक्तिः ॥ ३ ॥",
        "english_devnagari": "sa eva viśvasya bhavān vidhatteguṇapravāheṇa vibhaktavīryaḥsargādyanīho'vitathābhisandhiḥātmeśvaro'tarkya sahasraśaktiḥ",
        "verse_Syn": [
            "sa",
            "eva",
            "viśvasya",
            "bhavān",
            "vidhat",
            "te",
            "guṇa",
            "pravāheṇa",
            "vibhakta",
            "vīryaḥ",
            "sargād",
            "yan",
            "īho'",
            "avitathābhisandhiḥ",
            "ātmeśvaro'",
            "atarkya",
            "sahasraśaktiḥ"
        ],
        "translation": "It is with your power divided by the flow of your guṇas that you (of above description), remaining inactive, bring about the creation, maintenance and destruction of the universe; Your will power is effective; You are the controller of all the jīvas (for whose enjoyment you create the universe; Your powers are infinite and beyond comprehension.",
        "purport": ""
    },
    {
        "verse": "4",
        "devanagari": "स त्वं भृतो मे जठरेण नाथ । कथं नु यस्योदर एतदासीत् । विश्वं युगान्ते वटपत्र एकः । शेते स्म मायाशिशुरङ्घ्रिपानः ॥ ४ ॥",
        "english_devnagari": "sa tvaṃ bhṛto me jaṭhareṇa nāthakathaṃ nu yasyodara etadāsītviśvaṃ yugānte vaṭapatra ekaḥśete sma māyāśiśuraṅghripānaḥ",
        "verse_Syn": [
            "sa",
            "tvam",
            "bhṛto",
            "me",
            "jaṭhareṇa",
            "nātha",
            "katham",
            "nu",
            "yasyo",
            "dara",
            "etadā",
            "āsīt",
            "viśvam",
            "yugānte",
            "vaṭa",
            "patra",
            "ekaḥ",
            "śete",
            "sma",
            "māyā",
            "aśiśur",
            "aṅghripānaḥ"
        ],
        "translation": "Oh Lord, how was it possible that you were borne by me in my womb. It was your Māyā, you in whose stomach lay the whole of the universe, and who, at the end of Yugas (i.e. after the deluge set in) lay alone on a banyan leaf in the form of an infant sucking its toe.",
        "purport": ""
    },
    {
        "verse": "5",
        "devanagari": "त्वं देहतन्त्रः प्रशमाय पाप्मनां । निदेशभाजां च विभो विभूतये । यथावतारास्तव सूकरादयः । तथायमप्यात्म पथोपलब्धये ॥ ५ ॥",
        "english_devnagari": "tvaṃ dehatantraḥ praśamāya pāpmanāṃnideśabhājāṃ ca vibho vibhūtayeyathāvatārāstava sūkarādayaḥtathāyamapyātma pathopalabdhaye",
        "verse_Syn": [
            "tvam",
            "dehatantraḥ",
            "praśamāya",
            "pāpmanām",
            "nideśabhājām",
            "ca",
            "vibho",
            "vibhūtaye",
            "yathāvat",
            "ārās",
            "tava",
            "sūkarād",
            "ayaḥ",
            "tathā",
            "āyam",
            "apyāt",
            "ma",
            "patho",
            "upalabdhaye"
        ],
        "translation": "Oh Supreme Lord, you have assumed the corporeal form for the destruction of the wicked sinners and for the prosperity of those who obey your commands. Just as you have your (other) incarnations of Boar etc., this incarnation (of yours) is for showing the path of self-realization.",
        "purport": ""
    },
    {
        "verse": "6",
        "devanagari": "यन्नामधेयश्रवणानुकीर्तनाद् । यत्प्रह्वणाद् यत् स्मरणादपि क्वचित् । श्वादोऽपि सद्यः सवनाय कल्पते । कुतः पुनस्ते भगवन्नु दर्शनात् ॥ ६ ॥",
        "english_devnagari": "yannāmadheyaśravaṇānukīrtanādyatprahvaṇād yat smaraṇādapi kvacitśvādo'pi sadyaḥ savanāya kalpatekutaḥ punaste bhagavannu darśanāt",
        "verse_Syn": [
            "yannāmadheyaśravaṇānukīrtanād",
            "yat",
            "prahvaṇād",
            "yat",
            "smaraṇād",
            "api",
            "kva",
            "acit",
            "śvādo'",
            "api",
            "sadyaḥ",
            "savanāya",
            "kalpate",
            "kutaḥ",
            "punas",
            "te",
            "bhagavan",
            "nu",
            "darśanāt"
        ],
        "translation": "Oh glorious Lord, even a Cāṇḍāla (lit. a dog-eater) immediately becomes worthy (like a performer) of the Soma Sacrifice, if he has but once heard or uttered your name or bowed to you or remembered you. What need be said of a person (like me) who has (directly) seen you?",
        "purport": ""
    },
    {
        "verse": "7",
        "devanagari": "अहो बत श्वपचोऽतो गरीयान् । यज्जिह्वाग्रे वर्तते नाम तुभ्यम् । तेपुस्तपस्ते जुहुवुः सस्नुरार्या । ब्रह्मानूचुर्नाम गृणन्ति ये ते ॥ ७ ॥",
        "english_devnagari": "aho bata śvapaco'to garīyānyajjihvāgre vartate nāma tubhyamtepustapaste juhuvuḥ sasnurāryābrahmānūcurnāma gṛṇanti ye te",
        "verse_Syn": [
            "aho",
            "bata",
            "śvapaco'",
            "ato",
            "garīyān",
            "yajjihvāgre*va",
            "vartate",
            "nāma",
            "tubhyam",
            "tepus",
            "tapas",
            "te",
            "juhuvuḥ",
            "sasnur",
            "āryā",
            "brahmān",
            "ūcur",
            "nāma",
            "gṛṇanti",
            "ye",
            "te"
        ],
        "translation": "Oh how wonderful it is that even a Cāṇḍāla (the lowest-born person) becomes superior and worthy of respect simply because Your name is on the tip of his tongue. Those persons of noble behaviour who take your name have (the merit of having) performed penance, sacrifices and baths in holy waters, and Vedic studies (Or: It is as a result of doing these meritorious acts in the previous life that they take your name in this birth).",
        "purport": ""
    },
    {
        "verse": "8",
        "devanagari": "तं त्वामहं ब्रह्म परं पुमांसं । प्रत्यक्स्रोतस्यात्मनि संविभाव्यम् । स्वतेजसा ध्वस्तगुणप्रवाहं । वन्दे विष्णुं कपिलं वेदगर्भम् ॥ ८ ॥",
        "english_devnagari": "taṃ tvāmahaṃ brahma paraṃ pumāṃsaṃpratyaksrotasyātmani saṃvibhāvyamsvatejasā dhvastaguṇapravāhaṃvande viṣṇuṃ kapilaṃ vedagarbham",
        "verse_Syn": [
            "tam",
            "tvām",
            "aham",
            "brahma",
            "param",
            "pumāṃsam",
            "pratyaksrotasyā",
            "ātmani",
            "saṃvibhāvyam",
            "svatejasā",
            "dhvasta",
            "guṇa",
            "pravāham",
            "vande",
            "viṣṇum",
            "kapilam",
            "vedagarbham"
        ],
        "translation": "I pay obeisance to you, Kapila, who are the highest Brahman, the Supreme Man who are worthy of meditation in mind which is withdrawn from external objects, and who have dried up the flow of guṇas by your brilliance and who are Viṣṇu (who holds Vedas within him).",
        "purport": ""
    },
    {
        "verse": "9",
        "devanagari": "मैत्रेय उवाच । ईडितो भगवानेवं कपिलाख्यः परः पुमान् । वाचाविक्लवयेत्याह मातरं मातृवत्सलः ॥ ९ ॥",
        "english_devnagari": "maitreya uvācaīḍito bhagavānevaṃ kapilākhyaḥ paraḥ pumānvācāviklavayetyāha mātaraṃ mātṛvatsalaḥ",
        "verse_Syn": [
            "maitreya",
            "uvāca",
            "īḍito",
            "bhagavān",
            "evam",
            "kapilā",
            "akhyaḥ",
            "paraḥ",
            "pumān",
            "vācā",
            "aviklavaye",
            "ityā",
            "āha",
            "mātaram",
            "mātṛvatsalaḥ"
        ],
        "translation": "Maitreya said:\nThe Supreme Man called the venerable Kapila who was thus praised and who was affectionate to his mother, spoke thus to her in words deep insignificance (Or: with words choked up with emotions.).",
        "purport": ""
    },
    {
        "verse": "10",
        "devanagari": "कपिल उवाच । मार्गेणानेन मातस्ते सुसेव्येनोदितेन मे । आस्थितेन परां काष्ठां अचिराद् अवरोत्स्यसि ॥ १० ॥",
        "english_devnagari": "kapila uvācamārgeṇānena mātaste susevyenoditena meāsthitena parāṃ kāṣṭhāṃ acirād avarotsyasi",
        "verse_Syn": [
            "kapila",
            "uvāca",
            "mārgeṇā",
            "anena",
            "mātas",
            "te",
            "susevyeno",
            "uditena",
            "me",
            "āsthitena",
            "parām",
            "kāṣṭhām",
            "acirād",
            "avaro",
            "utsya",
            "si"
        ],
        "translation": "Kapila said:\nOh mother, I have explained to you the path which is easy to follow. By following this path, you will reach the highest stage (of being liberated while alive).",
        "purport": ""
    },
    {
        "verse": "11",
        "devanagari": "श्रद्धत्स्वैतन्मतं मह्यं जुष्टं यद्‍ब्रह्मवादिभिः । येन मां अभयं याया मृत्युमृच्छन्त्यतद्विदः ॥ ११ ॥",
        "english_devnagari": "śraddhatsvaitanmataṃ mahyaṃ juṣṭaṃ yad‍brahmavādibhiḥyena māṃ abhayaṃ yāyā mṛtyumṛcchantyatadvidaḥ",
        "verse_Syn": [
            "śraddhatsvaitanmatam*ma",
            "mahyam",
            "juṣṭam",
            "yad‍brahmavādibhiḥ",
            "yena",
            "mām",
            "abhayam",
            "yāyā",
            "mṛtyum",
            "ṛ",
            "cchan",
            "tyat",
            "ad",
            "vidaḥ"
        ],
        "translation": "Have faith in my doctrine which has been followed by the knowers of Brahman (or the Vedas). By following this you will attain to me who am without birth (i.e. eternal). Those who are ignorant about this path go to death (saṃsāra).",
        "purport": ""
    },
    {
        "verse": "12",
        "devanagari": "मैत्रेय उवाच । इति प्रदर्श्य भगवान् सतीं तां आत्मनो गतिम् । स्वमात्रा ब्रह्मवादिन्या कपिलोऽनुमतो ययौ ॥ १२ ॥",
        "english_devnagari": "maitreya uvācaiti pradarśya bhagavān satīṃ tāṃ ātmano gatimsvamātrā brahmavādinyā kapilo'numato yayau",
        "verse_Syn": [
            "maitreya",
            "uvāca",
            "iti",
            "pradarśya",
            "bhagavān",
            "satīm",
            "tām",
            "ātmano",
            "gatim",
            "svam",
            "ātrā",
            "brahmavādinyā",
            "kapilo'",
            "anumato",
            "yayau"
        ],
        "translation": "Maitreya said:\nThe venerable Kapila showed to his pious mother the path leading to Ātman. Having obtained the permission of his mother, who realized the Brahman, Kapila departed (from her hermitage).",
        "purport": ""
    },
    {
        "verse": "13",
        "devanagari": "सा चापि तनयोक्तेन योगादेशेन योगयुक् । तस्मिन् आश्रम आपीडे सरस्वत्याः समाहिता ॥ १३ ॥",
        "english_devnagari": "sā cāpi tanayoktena yogādeśena yogayuktasmin āśrama āpīḍe sarasvatyāḥ samāhitā",
        "verse_Syn": [
            "sā",
            "cāpi",
            "tanayo",
            "uktena",
            "yogā",
            "adeśena",
            "yogayuk",
            "tasmin",
            "āśrama",
            "āpīḍe",
            "sarasvatyāḥ",
            "samāhitā"
        ],
        "translation": "And in that hermitage which was like a flowerchaplet on the head of the Sarasvatī (river), she adopted Yogic practice in accordance with the guidance of her son, and became composed in mind.",
        "purport": ""
    },
    {
        "verse": "14",
        "devanagari": "अभीक्ष्ण अवगाहकपिशान् जटिलान् कुटिलालकान् । आत्मानं च उग्रतपसा बिभ्रती चीरिणं कृशम् ॥ १४ ॥",
        "english_devnagari": "abhīkṣṇa avagāhakapiśān jaṭilān kuṭilālakānātmānaṃ ca ugratapasā bibhratī cīriṇaṃ kṛśam",
        "verse_Syn": [
            "abhīkṣṇa",
            "avagāha",
            "kapiśān",
            "jaṭilān",
            "kuṭilālakān",
            "ātmānam",
            "ca",
            "ugratapasā",
            "bibhratī",
            "cīriṇam",
            "kṛśam"
        ],
        "translation": "She performed ablutions three times a day. Her curly hair became matted and tawny in colour. By severe penance her body became emaciated. She wore bark-garments.",
        "purport": ""
    },
    {
        "verse": "15",
        "devanagari": "प्रजापतेः कर्दमस्य तपोयोगविजृम्भितम् । स्वगार्हस्थ्यमनौपम्यं प्रार्थ्यं वैमानिकैरपि ॥ १५ ॥",
        "english_devnagari": "prajāpateḥ kardamasya tapoyogavijṛmbhitamsvagārhasthyamanaupamyaṃ prārthyaṃ vaimānikairapi",
        "verse_Syn": [
            "prajāpateḥ",
            "kardamasya",
            "tapoyoga",
            "vijṛmbhitam",
            "sva",
            "gārhasthyam",
            "anaupamyam",
            "prārthyam",
            "vaimānikair",
            "api"
        ],
        "translation": "The household comforts that were created by Prajāpati Kardama by means of his penance and Yoga were incomparable. They were covetable even to gods.",
        "purport": ""
    },
    {
        "verse": "16",
        "devanagari": "पयःफेननिभाः शय्या दान्ता रुक्मपरिच्छदाः । आसनानि च हैमानि सुस्पर्शास्तरणानि च ॥ १६ ॥",
        "english_devnagari": "payaḥphenanibhāḥ śayyā dāntā rukmaparicchadāḥāsanāni ca haimāni susparśāstaraṇāni ca",
        "verse_Syn": [
            "payaḥ",
            "phena",
            "nibhāḥ",
            "śayyā",
            "dāntā",
            "rukma",
            "paricchadāḥ",
            "āsanāni",
            "ca",
            "haimāni",
            "susparśās",
            "taraṇāni",
            "ca"
        ],
        "translation": "The beds were white and soft like the foam of milk. The ivory couches were chased with gold. The seats of gold were provided with soft cushions (covers).",
        "purport": ""
    },
    {
        "verse": "17",
        "devanagari": "स्वच्छस्फटिककुड्येषु महामारकतेषु च । रत्‍नप्रदीपा आभान्ति ललना रत्‍नसंयुताः ॥ १७ ॥",
        "english_devnagari": "svacchasphaṭikakuḍyeṣu mahāmārakateṣu carat‍napradīpā ābhānti lalanā rat‍nasaṃyutāḥ",
        "verse_Syn": [
            "svaccha",
            "sphaṭikakuḍyeṣu",
            "mahāmārakateṣu",
            "ca",
            "rat‍napradīpā*āb",
            "ābhā",
            "anti",
            "lalanā",
            "rat‍nasaṃyutāḥ"
        ],
        "translation": "In the walls of transparent crystals and very costly emeralds were shining jewel-lamps along with statues of beautiful damsels made of precious stones.",
        "purport": ""
    },
    {
        "verse": "18",
        "devanagari": "गृहोद्यानं कुसुमितै रम्यं बह्वमरद्रुमैः । कूजद् विहङ्गमिथुनं गायन् मत्तमधुव्रतम् ॥ १८ ॥",
        "english_devnagari": "gṛhodyānaṃ kusumitai ramyaṃ bahvamaradrumaiḥkūjad vihaṅgamithunaṃ gāyan mattamadhuvratam",
        "verse_Syn": [
            "gṛhodyānam",
            "kusumitai",
            "ramyam",
            "bahva",
            "amaradrumaiḥ",
            "kūjad",
            "vihaṅga",
            "mithunam",
            "gāyan",
            "mattam",
            "a",
            "dhu",
            "vratam"
        ],
        "translation": "The garden around the house looked beautiful with many blossoming celestial trees, on which couples of birds were warbling and the intoxicated black bees were humming sweetly.",
        "purport": ""
    },
    {
        "verse": "19",
        "devanagari": "यत्र प्रविष्टमात्मानं विबुधानुचरा जगुः । वाप्यां उत्पलगन्धिन्यां कर्दमेनोपलालितम् ॥ १९ ॥",
        "english_devnagari": "yatra praviṣṭamātmānaṃ vibudhānucarā jaguḥvāpyāṃ utpalagandhinyāṃ kardamenopalālitam",
        "verse_Syn": [
            "yatra",
            "praviṣṭam",
            "ātmānam",
            "vibudhānucarā",
            "jaguḥ",
            "vāpyām",
            "utpala",
            "gandhinyām",
            "kardameno",
            "upalālitam"
        ],
        "translation": "Where the followers of gods (Gandharvas) used to praise her when she, fondled by Kardama, entered in the swimming pool fragrant with lotuses.",
        "purport": ""
    },
    {
        "verse": "20",
        "devanagari": "हित्वा तदीप्सिततमं अप्याखण्डलयोषिताम् । किञ्चिच्चकार वदनं पुत्रविश्लेषणातुरा ॥ २० ॥",
        "english_devnagari": "hitvā tadīpsitatamaṃ apyākhaṇḍalayoṣitāmkiñciccakāra vadanaṃ putraviśleṣaṇāturā",
        "verse_Syn": [
            "hitvā",
            "tad",
            "īpsitatamam",
            "apyā",
            "ākhaṇḍalayo",
            "uṣitām",
            "kiñcic",
            "cakāra",
            "vadanam",
            "putra",
            "viśleṣaṇāt",
            "urā"
        ],
        "translation": "It (the household) was most covetable even to the queens of Indra. But she just abandoned it. Due to the anxiety caused by the separation of her son, she was dejected in appearance.",
        "purport": ""
    },
    {
        "verse": "21",
        "devanagari": "वनं प्रव्रजिते पत्यौ अपत्यविरहातुरा । ज्ञाततत्त्वाप्यभून्नष्टे वत्से गौरिव वत्सला ॥ २१ ॥",
        "english_devnagari": "vanaṃ pravrajite patyau apatyavirahāturājñātatattvāpyabhūnnaṣṭe vatse gauriva vatsalā",
        "verse_Syn": [
            "vanam",
            "pravrajite",
            "patyau",
            "apatya",
            "virahāt",
            "urā",
            "jñātatattvā",
            "apya",
            "abhūn",
            "naṣṭe",
            "vatse",
            "gauriva",
            "vatsalā"
        ],
        "translation": "As her husband left for the forest (after renouncing the world) Devahūti, though she realized the Truth (the Sāṃkhya Principles), became overanxious due to the separation from her son, like a calf-loving cow is fond after her young one.",
        "purport": ""
    },
    {
        "verse": "22",
        "devanagari": "तमेव ध्यायती देवं अपत्यं कपिलं हरिम् । बभूवाचिरतो वत्स निःस्पृहा तादृशे गृहे ॥ २२ ॥",
        "english_devnagari": "tameva dhyāyatī devaṃ apatyaṃ kapilaṃ harimbabhūvācirato vatsa niḥspṛhā tādṛśe gṛhe",
        "verse_Syn": [
            "tame",
            "iva",
            "dhyāyatī",
            "devam",
            "apatyam",
            "kapilam",
            "harim",
            "babhūvā",
            "acira",
            "to",
            "vatsa",
            "niḥspṛhā",
            "tādṛśe",
            "gṛhe"
        ],
        "translation": "Oh child (Vidura), she meditated upon her child Kapila who was the God Hari. In a short time, she became indifferent to that type of rich household.",
        "purport": ""
    },
    {
        "verse": "23",
        "devanagari": "ध्यायती भगवद्रूपं यदाह ध्यानगोचरम् । सुतः प्रसन्नवदनं समस्तव्यस्तचिन्तया ॥ २३ ॥",
        "english_devnagari": "dhyāyatī bhagavadrūpaṃ yadāha dhyānagocaramsutaḥ prasannavadanaṃ samastavyastacintayā",
        "verse_Syn": [
            "dhyāyatī",
            "bhagavad",
            "rūpam",
            "yadā",
            "aha",
            "dhyānagocaram",
            "sutaḥ",
            "prasanna",
            "vadanam",
            "samasta",
            "vyasta",
            "cintayā"
        ],
        "translation": "According to the guide-lines given by her son, she meditated upon the form of the gracious-looking Lord—the object of meditation—by the method of contemplating the complete form followed by concentration on the parts of it.[2]",
        "purport": "Footnote [2]:\nVide Supra III. 28.12-33."
    },
    {
        "verse": "24",
        "devanagari": "भक्तिप्रवाहयोगेन वैराग्येण बलीयसा । युक्तानुष्ठानजातेन ज्ञानेन ब्रह्महेतुना ॥ २४ ॥",
        "english_devnagari": "bhaktipravāhayogena vairāgyeṇa balīyasāyuktānuṣṭhānajātena jñānena brahmahetunā",
        "verse_Syn": [
            "bhakti",
            "pravāha",
            "yogena",
            "vairāgyeṇa",
            "balīyasā",
            "yuktān",
            "uṣṭhān",
            "ajātena",
            "jñānena",
            "brahmahe",
            "tu",
            "nā"
        ],
        "translation": "By means of stream or overflow of devotion, by powerful renunciation, and by knowledge which was produced by the proper observances of vows[3] leading to Brahma-hood.",
        "purport": "Footnote [3]:\nCf. Bhagavad Gītā 6.17."
    },
    {
        "verse": "25",
        "devanagari": "विशुद्धेन तदात्मानं आत्मना विश्वतोमुखम् । स्वानुभूत्या तिरोभूत मायागुणविशेषणम् ॥ २५ ॥",
        "english_devnagari": "viśuddhena tadātmānaṃ ātmanā viśvatomukhamsvānubhūtyā tirobhūta māyāguṇaviśeṣaṇam",
        "verse_Syn": [
            "viśuddhena",
            "tadāt",
            "mānam",
            "ātmanā",
            "viśvatomukham",
            "svānubhūtyā",
            "tiro",
            "bhūta",
            "māyā",
            "guṇaviśeṣa",
            "ṇam"
        ],
        "translation": "Her mind became pure. She was then lost in the meditation of all-pervading Atman who by his essential light removes the limitations of the guṇas of Māyā.",
        "purport": ""
    },
    {
        "verse": "26",
        "devanagari": "ब्रह्मण्यवस्थितमतिः भगवति आत्मसंश्रये । निवृत्तजीवापत्तित्वात् क्षीणक्लेशाऽप्त निर्वृतिः ॥ २६ ॥",
        "english_devnagari": "brahmaṇyavasthitamatiḥ bhagavati ātmasaṃśrayenivṛttajīvāpattitvāt kṣīṇakleśā'pta nirvṛtiḥ",
        "verse_Syn": [
            "brahmaṇya",
            "avasthita",
            "matiḥ",
            "bhagavati",
            "ātma",
            "saṃśraye",
            "nivṛtta",
            "jīvā",
            "āpatti",
            "tvāt",
            "kṣīṇakleśā'pta*ni",
            "nirvṛtiḥ"
        ],
        "translation": "Her mind became steadied in the glorious Brahman which is the shelter of all the jīvas. As she superseded her state of being a jīva, all her afflictions were over and she attained to the blessed stage.",
        "purport": ""
    },
    {
        "verse": "27",
        "devanagari": "नित्यारूढसमाधित्वात् परावृत्तगुणभ्रमा । न सस्मार तदाऽत्मानं स्वप्ने दृष्टमिवोत्थितः ॥ २७ ॥",
        "english_devnagari": "nityārūḍhasamādhitvāt parāvṛttaguṇabhramāna sasmāra tadā'tmānaṃ svapne dṛṣṭamivotthitaḥ",
        "verse_Syn": [
            "nityā",
            "ārūḍha",
            "samādhitvāt",
            "parāvṛttaguṇabhramā",
            "na",
            "sasmāra",
            "tadā'",
            "atmān",
            "am",
            "svapne",
            "dṛṣṭam",
            "ivo",
            "utthitaḥ"
        ],
        "translation": "As she was always engaged in continuous meditation and her delusion due to guṇas was dispelled, at that time she did not remember her body, just as an object seen in a dream (is found to be unreal) after waking up.",
        "purport": ""
    },
    {
        "verse": "28",
        "devanagari": "तद्देहः परतः पोषोऽपि अकृशश्चाध्यसम्भवात् । बभौ मलैरवच्छन्नः सधूम इव पावकः ॥ २८ ॥",
        "english_devnagari": "taddehaḥ parataḥ poṣo'pi akṛśaścādhyasambhavātbabhau malairavacchannaḥ sadhūma iva pāvakaḥ",
        "verse_Syn": [
            "tad",
            "dehaḥ",
            "parataḥ",
            "poṣo'",
            "api",
            "akṛśaś",
            "cā",
            "adhya",
            "asambhavāt",
            "babhau",
            "malair",
            "avacchannaḥ",
            "sadhūma",
            "iva",
            "pāvakaḥ"
        ],
        "translation": "Her body was fed by others (viz. Vidyādhara damsels who were produced by Kardama for attendance upon her). As she was free from diseases, she did not become emaciated. Her body was covered with filth. She looked like a fire covered with smoke.",
        "purport": ""
    },
    {
        "verse": "29",
        "devanagari": "स्वाङ्गं तपोयोगमयं मुक्तकेशं गताम्बरम् । दैवगुप्तं न बुबुधे वासुदेवप्रविष्टधीः ॥ २९ ॥",
        "english_devnagari": "svāṅgaṃ tapoyogamayaṃ muktakeśaṃ gatāmbaramdaivaguptaṃ na bubudhe vāsudevapraviṣṭadhīḥ",
        "verse_Syn": [
            "svāṅgam",
            "tapoyogam",
            "ayam",
            "muktakeśam",
            "gatām",
            "baram",
            "daiva",
            "guptam",
            "na",
            "bubudhe",
            "vāsudeva",
            "praviṣṭa",
            "dhīḥ"
        ],
        "translation": "Her mind was so deeply entered (i.e. absorbed) in Vāsudeva that she was not conscious of her body. She had so completely given herself up to penance and Yoga that her hair fell dishevelled and clothes were dropped aṇd she was protected by her previous karma (daiva).",
        "purport": ""
    },
    {
        "verse": "30",
        "devanagari": "एवं सा कपिलोक्तेन मार्गेणाचिरतः परम् । आत्मानं ब्रह्मनिर्वाणं भगवन्तं अवाप ह ॥ ३० ॥",
        "english_devnagari": "evaṃ sā kapiloktena mārgeṇācirataḥ paramātmānaṃ brahmanirvāṇaṃ bhagavantaṃ avāpa ha",
        "verse_Syn": [
            "evam",
            "sā",
            "kapilo",
            "uktena",
            "mārgeṇā",
            "acira",
            "taḥ",
            "param",
            "ātmānam",
            "brahmanirvāṇam",
            "bhagavantam",
            "avāpa",
            "ha"
        ],
        "translation": "In this way she progressed by the path expounded by Kapila. Within a short period she attained to the Supreme Soul, the Brahman, the glorious Lord; the stage called Nirvāṇa.",
        "purport": ""
    },
    {
        "verse": "31",
        "devanagari": "तद्वीरासीत् पुण्यतमं क्षेत्रं त्रैलोक्यविश्रुतम् । नाम्ना सिद्धपदं यत्र सा संसिद्धिमुपेयुषी ॥ ३१ ॥",
        "english_devnagari": "tadvīrāsīt puṇyatamaṃ kṣetraṃ trailokyaviśrutamnāmnā siddhapadaṃ yatra sā saṃsiddhimupeyuṣī",
        "verse_Syn": [
            "tad",
            "vīrā",
            "āsīt",
            "puṇyatamam",
            "kṣetram",
            "trailokya",
            "viśrutam",
            "nāmnā",
            "siddhapadam",
            "yatra",
            "sā",
            "saṃsiddhim",
            "upeyuṣī"
        ],
        "translation": "Oh warrior (Vidura), the place called Siddhapada where she attained the Liberation became famous as the holiest place in the three worlds.",
        "purport": ""
    },
    {
        "verse": "32",
        "devanagari": "तस्यास्तद्योगविधुतमार्त्यं मर्त्यमभूत्सरित् । स्रोतसां प्रवरा सौम्य सिद्धिदा सिद्धसेविता ॥ ३२ ॥",
        "english_devnagari": "tasyāstadyogavidhutamārtyaṃ martyamabhūtsaritsrotasāṃ pravarā saumya siddhidā siddhasevitā",
        "verse_Syn": [
            "tasyās",
            "tad",
            "yoga",
            "vidhutamārtyam",
            "martyam",
            "abhūt",
            "sarit",
            "srotasām",
            "pravarā",
            "saumya",
            "siddhidā",
            "siddha",
            "sevitā"
        ],
        "translation": "Oh gentle Vidura, her mortal body from which impurities were eliminated by Yoga, was transformed into a river, a prominent one among many rivers. It blesses one with siddhis and is resorted to by Siddhas.",
        "purport": ""
    },
    {
        "verse": "33",
        "devanagari": "कपिलोऽपि महायोगी भगवान् पितुराश्रमात् । मातरं समनुज्ञाप्य प्राग् उदीचीं दिशं ययौ ॥ ३३ ॥",
        "english_devnagari": "kapilo'pi mahāyogī bhagavān piturāśramātmātaraṃ samanujñāpya prāg udīcīṃ diśaṃ yayau",
        "verse_Syn": [
            "kapilo'",
            "api",
            "mahāyogī",
            "bhagavān",
            "pitur",
            "āśramāt",
            "mātaram",
            "samanujñā",
            "apya",
            "prāg",
            "udīcīm",
            "diśam",
            "yayau"
        ],
        "translation": "Even glorious Kapila, the great Yogin, obtained the permission of his mother to depart from his father’s hermitage and proceeded to the northern direction.",
        "purport": ""
    },
    {
        "verse": "34",
        "devanagari": "सिद्धचारण गन्धर्वैः मुनिभिश्च अप्सरोगणैः । स्तूयमानः समुद्रेण दत्तार्हणनिकेतनः ॥ ३४ ॥",
        "english_devnagari": "siddhacāraṇa gandharvaiḥ munibhiśca apsarogaṇaiḥstūyamānaḥ samudreṇa dattārhaṇaniketanaḥ",
        "verse_Syn": [
            "siddha",
            "cāraṇa",
            "gandharvaiḥ",
            "munibhiś",
            "ca",
            "apsarogaṇaiḥ",
            "stūyamānaḥ",
            "samudreṇa",
            "dattā",
            "arhaṇa",
            "niketanaḥ"
        ],
        "translation": "He was praised by multitude of Siddhas, Cāraṇas, Gandharvas, sages and celestial nymphs. He was also respectfully received by the sea and was presented a valuable dwelling place.",
        "purport": ""
    },
    {
        "verse": "35",
        "devanagari": "आस्ते योगं समास्थाय साङ्ख्याचार्यैरभिष्टुतः । त्रयाणामपि लोकानां उपशान्त्यै समाहितः ॥ ३५ ॥",
        "english_devnagari": "āste yogaṃ samāsthāya sāṅkhyācāryairabhiṣṭutaḥtrayāṇāmapi lokānāṃ upaśāntyai samāhitaḥ",
        "verse_Syn": [
            "āste",
            "yogam",
            "samās",
            "thāya",
            "sāṅkhyācāryair",
            "abhiṣṭutaḥ",
            "trayāṇām",
            "api",
            "lokānām",
            "upaśāntyai",
            "samāhitaḥ"
        ],
        "translation": "Kapila stays there practising Yoga. He is highly eulogized by the great teachers of Sāṃkhya School. For the peace and tranquillity of the three worlds, he lives there (absorbed) in meditation.",
        "purport": ""
    },
    {
        "verse": "36",
        "devanagari": "एतन्निगदितं तात यत्पृष्टोऽहं तवानघ । कपिलस्य च संवादो देवहूत्याश्च पावनः ॥ ३६ ॥",
        "english_devnagari": "etannigaditaṃ tāta yatpṛṣṭo'haṃ tavānaghakapilasya ca saṃvādo devahūtyāśca pāvanaḥ",
        "verse_Syn": [
            "etan",
            "nigaditam",
            "tāta",
            "yat",
            "pṛṣṭo'",
            "aham",
            "tavān",
            "agha",
            "kapilasya",
            "ca",
            "saṃvādo",
            "devahūtyāś",
            "ca",
            "pāvanaḥ"
        ],
        "translation": "Oh child (Vidura), as per your query I have narrated to you the sacred dialogue between Kapila and Deva- hūti, Oh sinless one.",
        "purport": ""
    },
    {
        "verse": "37",
        "devanagari": "य इदमनुशृणोति योऽभिधत्ते । कपिलमुनेर्मतं आत्मयोगगुह्यम् । भगवति कृतधीः सुपर्णकेतौ । उपलभते भगवत् पदारविन्दम् ॥ ३७ ॥",
        "english_devnagari": "ya idamanuśṛṇoti yo'bhidhattekapilamunermataṃ ātmayogaguhyambhagavati kṛtadhīḥ suparṇaketauupalabhate bhagavat padāravindam",
        "verse_Syn": [
            "ya",
            "idam",
            "anu",
            "śṛṇoti",
            "yo'",
            "abhi",
            "dhatte",
            "kapilam",
            "une",
            "īrma",
            "tam",
            "ātmayoga",
            "guhyam",
            "bhagavati",
            "kṛtadhīḥ",
            "suparṇaketau",
            "upala",
            "bha",
            "te",
            "bhagavat",
            "padāravindam"
        ],
        "translation": "He who listens to this or narrates this doctrine of the Sage Kapila regarding the secret knowledge about the Ātman, becomes able to concentrate his mind upon the venerable Lord whose banner has the emblem of Garuḍa, and he attains to the lotus-like feet of the glorious Lord.\n[back to top]",
        "purport": ""
    }
]
